xyz2rast
